phone_number_validator_dirso/__init__.py
phone_number_validator_dirso/main.py
phone_number_validator_dirso/validator.py
phone_number_validator_dirso-0.1.0.dist-info/METADATA
phone_number_validator_dirso-0.1.0.dist-info/WHEEL
phone_number_validator_dirso-0.1.0.dist-info/RECORD
