Metadata-Version: 2.1
Name: phone-number-validator-dirso
Version: 0.1.0
Summary: 
Author: khouri
Author-email: adilson.khouri.usp@gmail.com
Requires-Python: >=3.10,<4.0
Classifier: Programming Language :: Python :: 3
Classifier: Programming Language :: Python :: 3.10
Classifier: Programming Language :: Python :: 3.11
Classifier: Programming Language :: Python :: 3.12
Requires-Dist: requests (>=2.32.3,<3.0.0)
